{
  "swagger": "2.0",
  "info": {
    "title": "server, Version=1.0.0.0, Culture=neutral, PublicKeyToken=null",
    "version": "1.0"
  },
  "paths": {
    "/api/product": {
      "get": {
        "tags": [
          "Product"
        ],
        "produces": [
          "text/plain",
          "application/json",
          "text/json"
        ],
        "responses": {
          "200": {
            "description": "Success",
            "schema": {
              "type": "array",
              "items": {
                "$ref": "#/definitions/Product"
              }
            }
          }
        }
      }
    },
    "/api/product/{id}": {
      "get": {
        "tags": [
          "Product"
        ],
        "produces": [
          "text/plain",
          "application/json",
          "text/json"
        ],
        "parameters": [
          {
            "in": "path",
            "name": "id",
            "required": true,
            "type": "integer",
            "format": "int32"
          }
        ],
        "responses": {
          "200": {
            "description": "Success",
            "schema": {
              "$ref": "#/definitions/Product"
            }
          }
        }
      }
    },
    "/api/region": {
      "get": {
        "tags": [
          "Region"
        ],
        "produces": [
          "text/plain",
          "application/json",
          "text/json"
        ],
        "responses": {
          "200": {
            "description": "Success",
            "schema": {
              "type": "array",
              "items": {
                "$ref": "#/definitions/Region"
              }
            }
          }
        }
      }
    },
    "/api/region/{id}": {
      "get": {
        "tags": [
          "Region"
        ],
        "produces": [
          "text/plain",
          "application/json",
          "text/json"
        ],
        "parameters": [
          {
            "in": "path",
            "name": "id",
            "required": true,
            "type": "integer",
            "format": "int32"
          }
        ],
        "responses": {
          "200": {
            "description": "Success",
            "schema": {
              "$ref": "#/definitions/Region"
            }
          }
        }
      }
    },
    "/api/user/register": {
      "post": {
        "tags": [
          "User"
        ],
        "consumes": [
          "application/json",
          "text/json",
          "application/*+json"
        ],
        "parameters": [
          {
            "in": "body",
            "name": "body",
            "schema": {
              "$ref": "#/definitions/RegisterUserDto"
            }
          }
        ],
        "responses": {
          "200": {
            "description": "Success"
          }
        }
      }
    },
    "/api/user/login": {
      "post": {
        "tags": [
          "User"
        ],
        "consumes": [
          "application/json",
          "text/json",
          "application/*+json"
        ],
        "parameters": [
          {
            "in": "body",
            "name": "body",
            "schema": {
              "$ref": "#/definitions/LoginDto"
            }
          }
        ],
        "responses": {
          "200": {
            "description": "Success"
          }
        }
      }
    },
    "/api/user/{id}/update": {
      "post": {
        "tags": [
          "User"
        ],
        "consumes": [
          "application/json",
          "text/json",
          "application/*+json"
        ],
        "parameters": [
          {
            "in": "path",
            "name": "id",
            "required": true,
            "type": "integer",
            "format": "int32"
          },
          {
            "in": "body",
            "name": "body",
            "schema": {
              "$ref": "#/definitions/UpdateUserDto"
            }
          }
        ],
        "responses": {
          "200": {
            "description": "Success"
          }
        }
      }
    },
    "/WeatherForecast": {
      "get": {
        "tags": [
          "WeatherForecast"
        ],
        "operationId": "GetWeatherForecast",
        "produces": [
          "text/plain",
          "application/json",
          "text/json"
        ],
        "responses": {
          "200": {
            "description": "Success",
            "schema": {
              "type": "array",
              "items": {
                "$ref": "#/definitions/WeatherForecast"
              }
            }
          }
        }
      }
    }
  },
  "definitions": {
    "LoginDto": {
      "type": "object",
      "properties": {
        "email": {
          "type": "string"
        },
        "password": {
          "type": "string"
        }
      }
    },
    "Product": {
      "type": "object",
      "properties": {
        "id": {
          "format": "int32",
          "type": "integer"
        },
        "name": {
          "type": "string"
        },
        "isDeleted": {
          "type": "boolean"
        },
        "userId": {
          "format": "int32",
          "type": "integer"
        },
        "user": {
          "$ref": "#/definitions/User"
        }
      }
    },
    "Region": {
      "type": "object",
      "properties": {
        "id": {
          "format": "int32",
          "type": "integer"
        },
        "name": {
          "type": "string"
        }
      }
    },
    "RegisterUserDto": {
      "type": "object",
      "properties": {
        "name": {
          "type": "string"
        },
        "email": {
          "type": "string"
        },
        "password": {
          "type": "string"
        },
        "confirmPassword": {
          "type": "string"
        },
        "birthDate": {
          "format": "date-time",
          "type": "string"
        },
        "roleId": {
          "format": "int32",
          "type": "integer"
        },
        "regionId": {
          "format": "int32",
          "type": "integer"
        }
      }
    },
    "Role": {
      "type": "object",
      "properties": {
        "id": {
          "format": "int32",
          "type": "integer"
        },
        "name": {
          "type": "string"
        }
      }
    },
    "UpdateUserDto": {
      "type": "object",
      "properties": {
        "name": {
          "type": "string"
        },
        "sex": {
          "type": "string"
        },
        "regionId": {
          "format": "int32",
          "type": "integer"
        }
      }
    },
    "User": {
      "type": "object",
      "properties": {
        "id": {
          "format": "int32",
          "type": "integer"
        },
        "name": {
          "type": "string"
        },
        "email": {
          "type": "string"
        },
        "passwordHash": {
          "type": "string"
        },
        "birthDate": {
          "format": "date-time",
          "type": "string"
        },
        "sex": {
          "type": "string"
        },
        "isDeleted": {
          "type": "boolean"
        },
        "roleId": {
          "format": "int32",
          "type": "integer"
        },
        "role": {
          "$ref": "#/definitions/Role"
        },
        "regionId": {
          "format": "int32",
          "type": "integer"
        },
        "region": {
          "$ref": "#/definitions/Region"
        }
      }
    },
    "WeatherForecast": {
      "type": "object",
      "properties": {
        "date": {
          "format": "date-time",
          "type": "string"
        },
        "temperatureC": {
          "format": "int32",
          "type": "integer"
        },
        "temperatureF": {
          "format": "int32",
          "type": "integer",
          "readOnly": true
        },
        "summary": {
          "type": "string"
        }
      }
    }
  }
}